<annotation>
	<folder>licenses</folder>
	<filename>punjabjagdish.jpg</filename>
	<path>/Users/apple/Downloads/licenses/punjabjagdish.jpg</path>
	<source>
		<database>Unknown</database>
	</source>
	<size>
		<width>4096</width>
		<height>2304</height>
		<depth>3</depth>
	</size>
	<segmented>0</segmented>
	<object>
		<name>text</name>
		<pose>Unspecified</pose>
		<truncated>0</truncated>
		<difficult>0</difficult>
		<bndbox>
			<xmin>1908</xmin>
			<ymin>658</ymin>
			<xmax>2576</xmax>
			<ymax>762</ymax>
		</bndbox>
	</object>
	<object>
		<name>text</name>
		<pose>Unspecified</pose>
		<truncated>0</truncated>
		<difficult>0</difficult>
		<bndbox>
			<xmin>1912</xmin>
			<ymin>766</ymin>
			<xmax>2744</xmax>
			<ymax>878</ymax>
		</bndbox>
	</object>
	<object>
		<name>text</name>
		<pose>Unspecified</pose>
		<truncated>0</truncated>
		<difficult>0</difficult>
		<bndbox>
			<xmin>1900</xmin>
			<ymin>1050</ymin>
			<xmax>2932</xmax>
			<ymax>1314</ymax>
		</bndbox>
	</object>
	<object>
		<name>text</name>
		<pose>Unspecified</pose>
		<truncated>0</truncated>
		<difficult>0</difficult>
		<bndbox>
			<xmin>1312</xmin>
			<ymin>1602</ymin>
			<xmax>1548</xmax>
			<ymax>1686</ymax>
		</bndbox>
	</object>
	<object>
		<name>text</name>
		<pose>Unspecified</pose>
		<truncated>0</truncated>
		<difficult>0</difficult>
		<bndbox>
			<xmin>1676</xmin>
			<ymin>1610</ymin>
			<xmax>1856</xmax>
			<ymax>1678</ymax>
		</bndbox>
	</object>
</annotation>
